CHANGES
LICENSE
MANIFEST.in
README.txt
setup.cfg
setup.py
pbp/__init__.py
pbp.skels.egg-info/PKG-INFO
pbp.skels.egg-info/SOURCES.txt
pbp.skels.egg-info/dependency_links.txt
pbp.skels.egg-info/entry_points.txt
pbp.skels.egg-info/namespace_packages.txt
pbp.skels.egg-info/not-zip-safe
pbp.skels.egg-info/requires.txt
pbp.skels.egg-info/top_level.txt
pbp/skels/README.txt
pbp/skels/__init__.py
pbp/skels/base.py
pbp/skels/templates.py
pbp/skels/docs/README.txt
pbp/skels/doctests/README.txt
pbp/skels/doctests/package.txt
pbp/skels/doctests/recipe.txt
pbp/skels/tests/__init__.py
pbp/skels/tests/test_skelsdocs.py
pbp/skels/tests/test_skelsdocstrings.py
pbp/skels/tmpl/design/+short_name+.txt_tmpl
pbp/skels/tmpl/module/+short_name+.txt_tmpl
pbp/skels/tmpl/package/setup.py_tmpl
pbp/skels/tmpl/package/+namespace_package+/__init__.py_tmpl
pbp/skels/tmpl/package/+namespace_package+/+package+/README.txt
pbp/skels/tmpl/package/+namespace_package+/+package+/__init__.py_tmpl
pbp/skels/tmpl/recipe/+short_name+.txt_tmpl
pbp/skels/tmpl/tutorial/+short_name+.txt_tmpl