Metadata-Version: 1.0
Name: pbp.skels
Version: 0.2.4
Summary: Expert Python Programming - Skeletons used in the book
Home-page: http://atomisator.ziade.org
Author: Tarek Ziadé
Author-email: tarek@ziade.org
License: GPL
Platform: UNKNOWN
Classifier: Programming Language :: Python
Classifier: Topic :: Software Development :: Libraries :: Python Modules
